hera_tda-0.0.2.dist-info/top_level.txt
hera_tda-0.0.2.dist-info/WHEEL
hera_tda-0.0.2.dist-info/RECORD
hera_tda-0.0.2.dist-info/LICENSE
hera_tda-0.0.2.dist-info/METADATA
hera_tda/__init__.py
hera_tda/bottleneck.cpython-310-x86_64-linux-gnu.so
hera_tda/wasserstein.cpython-310-x86_64-linux-gnu.so
hera_tda/_version.py
