Metadata-Version: 2.1
Name: hera-tda
Version: 0.0.2
Summary: Python bindings for Hera
Home-page: https://github.com/CompTop/pyhera
Author: Brad Nelson
Author-email: bradnelson@uchicago.edu
License: UNKNOWN
Project-URL: Bug Tracker, https://github.com/CompTop/pyhera/issues
Keywords: algebraic topology,topological data analysis,bottleneck distance,wasserstein distance,persistence barcode,persistence diagram
Platform: UNKNOWN
Classifier: Development Status :: 3 - Alpha
Classifier: Intended Audience :: Developers
Classifier: Intended Audience :: Education
Classifier: Intended Audience :: Science/Research
Classifier: Topic :: Software Development :: Libraries :: Python Modules
Classifier: Topic :: Utilities
Classifier: Topic :: Scientific/Engineering :: Mathematics
Classifier: Programming Language :: C++
Classifier: Programming Language :: Python :: 3
Classifier: Programming Language :: Python :: 3.7
Classifier: Programming Language :: Python :: 3.8
Classifier: Programming Language :: Python :: 3.9
Classifier: Programming Language :: Python :: 3.10
Classifier: License :: OSI Approved :: BSD License
Classifier: Operating System :: POSIX :: Linux
Classifier: Operating System :: MacOS :: MacOS X
Requires-Python: >=3.7
License-File: LICENSE
License-File: hera/license.txt
